LICENSE
MANIFEST.in
README.md
setup.cfg
setup.py
django_urlid_graph.egg-info/PKG-INFO
django_urlid_graph.egg-info/SOURCES.txt
django_urlid_graph.egg-info/dependency_links.txt
django_urlid_graph.egg-info/requires.txt
django_urlid_graph.egg-info/top_level.txt
urlid_graph/__init__.py
urlid_graph/admin.py
urlid_graph/apps.py
urlid_graph/db_router.py
urlid_graph/exceptions.py
urlid_graph/formatting.py
urlid_graph/graph_db.py
urlid_graph/log.py
urlid_graph/mixins.py
urlid_graph/models.py
urlid_graph/network_vis_config.py
urlid_graph/serializers.py
urlid_graph/settings.py
urlid_graph/urls.py
urlid_graph/utils.py
urlid_graph/views.py
urlid_graph/management/commands/custom_index.py
urlid_graph/management/commands/export_config.py
urlid_graph/management/commands/import_config.py
urlid_graph/management/commands/import_data.py
urlid_graph/management/commands/import_objects.py
urlid_graph/management/commands/import_relationships.py
urlid_graph/management/commands/index_objects.py
urlid_graph/management/commands/remove_duplicates.py
urlid_graph/management/commands/update_stats.py
urlid_graph/migrations/0001_initial.py
urlid_graph/migrations/0002_alter_elementconfig_options_alter_entity_options_and_more.py
urlid_graph/migrations/0003_joblog_jobstep.py
urlid_graph/migrations/0004_alter_joblog_id_alter_logstep_message.py
urlid_graph/migrations/0005_alter_joblog_options_alter_logstep_options.py
urlid_graph/migrations/0006_alter_elementconfig_config_type.py
urlid_graph/migrations/__init__.py