Metadata-Version: 2.1
Name: django-urlid-graph
Version: 0.5.11
Summary: Django-based API to serve URLid + graph database
Home-page: https://github.com/PythonicCafe/django-urlid-graph/
Author: Álvaro Justen
Author-email: alvarojusten@gmail.com
License: GNU Lesser General Public License v3 (LGPLv3)
Keywords: graph data database api
Classifier: Environment :: Web Environment
Classifier: Framework :: Django
Classifier: Framework :: Django :: 3.2
Classifier: Intended Audience :: Developers
Classifier: License :: OSI Approved :: GNU Lesser General Public License v3 (LGPLv3)
Classifier: Operating System :: OS Independent
Classifier: Programming Language :: Python
Classifier: Programming Language :: Python :: 3
Classifier: Programming Language :: Python :: 3 :: Only
Classifier: Programming Language :: Python :: 3.6
Classifier: Programming Language :: Python :: 3.7
Classifier: Programming Language :: Python :: 3.8
Classifier: Topic :: Internet :: WWW/HTTP
Classifier: Topic :: Internet :: WWW/HTTP :: Dynamic Content
Requires-Python: >=3.7
License-File: LICENSE
Requires-Dist: Django>=3.2.0
Requires-Dist: agensgraph
Requires-Dist: cached-property
Requires-Dist: click
Requires-Dist: dj-database-url
Requires-Dist: djangorestframework
Requires-Dist: psycopg2-binary
Requires-Dist: python-decouple
Requires-Dist: requests
Requires-Dist: requests-cache
Requires-Dist: tqdm
